{
  "an9.31:0.1": "<article id='an9.31'><header><ul><li class='division'>{}</li>",
  "an9.31:0.2": "<li>{}</li></ul>",
  "an9.31:0.3": "<h1 class='sutta-title'>{}</h1></header>",
  "an9.31:1.1": "<p>{}",
  "an9.31:1.2": "{}</p>",
  "an9.31:1.3": "<p>{}</p>",
  "an9.31:1.4": "<p>{}</p>",
  "an9.31:1.5": "<p>{}</p>",
  "an9.31:1.6": "<p>{}</p>",
  "an9.31:1.7": "<p>{}</p>",
  "an9.31:1.8": "<p>{}</p>",
  "an9.31:1.9": "<p>{}</p>",
  "an9.31:1.10": "<p>{}</p>",
  "an9.31:1.11": "<p>{}</p>",
  "an9.31:1.12": "<p>{}</p>",
  "an9.31:1.13": "<p class='endsection'>{}</p>",
  "an9.31:1.14": "<p class='endsection'>{}</p>",
  "an9.31:2.0": "<p class='uddana-intro'>{}</p>",
  "an9.31:2.1": "<blockquote class='uddanagatha'><p>{}<br>",
  "an9.31:2.2": "{}<br>",
  "an9.31:2.3": "{}<br>",
  "an9.31:2.4": "{}</p></blockquote></article>"
}