{
  "tha-ap46:1.1": "bj36.172, csp1ed20.108, csp2ed20.108, mc1.139, ms20Ap1_1284, msdiv70, sc1, sya32.139",
  "tha-ap46:2.1": "ms20Ap1_1285, msdiv71, sc2",
  "tha-ap46:3.1": "ms20Ap1_1286, msdiv72, sc3",
  "tha-ap46:4.1": "ms20Ap1_1287, msdiv73, sc4",
  "tha-ap46:5.1": "ms20Ap1_1288, msdiv74, ndp27.116, sc5",
  "tha-ap46:6.1": "ms20Ap1_1289, msdiv75, sc6",
  "tha-ap46:7.1": "dr32.146, ms20Ap1_1290, msdiv76, sc7, vri57.96",
  "tha-ap46:8.1": "ms20Ap1_1291, sc8",
  "tha-ap46:9.1": "ms20Ap1_1292, sc9"
}