{
  "patthana4.7:1.1": "sc1, ms39P4_1526, msdiv1",
  "patthana4.7:2.1": "sc2, ms39P4_1527",
  "patthana4.7:3.1": "sc3, ms39P4_1528",
  "patthana4.7:4.1": "sc4, ms39P4_1529, msdiv2",
  "patthana4.7:5.1": "sc5, ms39P4_1530",
  "patthana4.7:6.1": "sc6, ms39P4_1531",
  "patthana4.7:7.1": "sc7, ms39P4_1532",
  "patthana4.7:8.1": "sc8, ms39P4_1533",
  "patthana4.7:9.1": "sc9, ms39P4_1534, msdiv3",
  "patthana4.7:10.1": "sc10, ms39P4_1535",
  "patthana4.7:11.1": "sc11, ms39P4_1536, msdiv4",
  "patthana4.7:12.1": "sc12, ms39P4_1537",
  "patthana4.7:13.1": "sc13, ms39P4_1538",
  "patthana4.7:14.1": "sc14, ms39P4_1539, msdiv5",
  "patthana4.7:15.1": "sc15, ms39P4_1540",
  "patthana4.7:16.1": "sc16, ms39P4_1541, msdiv6",
  "patthana4.7:17.1": "sc17, ms39P4_1542",
  "patthana4.7:18.1": "sc18, ms39P4_1543",
  "patthana4.7:19.1": "sc19, ms39P4_1544, msdiv7",
  "patthana4.7:20.1": "sc20, ms39P4_1545",
  "patthana4.7:21.1": "sc21, ms39P4_1546, msdiv8",
  "patthana4.7:22.1": "sc22, ms39P4_1547",
  "patthana4.7:23.1": "sc23, ms39P4_1548",
  "patthana4.7:24.1": "sc24, ms39P4_1549, msdiv9",
  "patthana4.7:25.1": "sc25, ms39P4_1550",
  "patthana4.7:26.1": "sc26, ms39P4_1551",
  "patthana4.7:27.1": "sc27, ms39P4_1552, msdiv10",
  "patthana4.7:28.1": "sc28, ms39P4_1553",
  "patthana4.7:29.1": "sc29, ms39P4_1554",
  "patthana4.7:30.1": "sc30, ms39P4_1555, msdiv11",
  "patthana4.7:31.1": "sc31, ms39P4_1556",
  "patthana4.7:32.1": "sc32, ms39P4_1557",
  "patthana4.7:33.1": "sc33, ms39P4_1558, msdiv12",
  "patthana4.7:34.1": "sc34, ms39P4_1559",
  "patthana4.7:35.1": "sc35, ms39P4_1560",
  "patthana4.7:36.1": "sc36, ms39P4_1561, msdiv13",
  "patthana4.7:37.1": "sc37, ms39P4_1562",
  "patthana4.7:38.1": "sc38, ms39P4_1563, msdiv14",
  "patthana4.7:39.1": "sc39, ms39P4_1564",
  "patthana4.7:40.1": "sc40, ms39P4_1565",
  "patthana4.7:41.1": "sc41, ms39P4_1566",
  "patthana4.7:42.1": "sc42, ms39P4_1567",
  "patthana4.7:43.1": "sc43, ms39P4_1568",
  "patthana4.7:44.1": "sc44, ms39P4_1569, msdiv15",
  "patthana4.7:45.1": "sc45, ms39P4_1570",
  "patthana4.7:46.1": "sc46, ms39P4_1571, msdiv16",
  "patthana4.7:47.1": "sc47, ms39P4_1572",
  "patthana4.7:48.1": "sc48, ms39P4_1573",
  "patthana4.7:49.1": "sc49, ms39P4_1574, msdiv17",
  "patthana4.7:50.1": "sc50, ms39P4_1575",
  "patthana4.7:51.1": "sc51, ms39P4_1576, msdiv18",
  "patthana4.7:52.1": "sc52, ms39P4_1577",
  "patthana4.7:53.1": "sc53, ms39P4_1578, msdiv19",
  "patthana4.7:54.1": "sc54, ms39P4_1579, msdiv20",
  "patthana4.7:55.1": "sc55, ms39P4_1580",
  "patthana4.7:56.1": "sc56, ms39P4_1581",
  "patthana4.7:57.1": "sc57, ms39P4_1582, msdiv21",
  "patthana4.7:58.1": "sc58, ms39P4_1583",
  "patthana4.7:59.1": "sc59, ms39P4_1584, msdiv22",
  "patthana4.7:60.1": "sc60, ms39P4_1585",
  "patthana4.7:61.1": "sc61, ms39P4_1586",
  "patthana4.7:62.1": "sc62, ms39P4_1587, msdiv23",
  "patthana4.7:63.1": "sc63, ms39P4_1588, msdiv24",
  "patthana4.7:64.1": "sc64, ms39P4_1589",
  "patthana4.7:65.1": "sc65, ms39P4_1590",
  "patthana4.7:66.1": "sc66, ms39P4_1591",
  "patthana4.7:67.1": "sc67, ms39P4_1592",
  "patthana4.7:68.1": "sc68, ms39P4_1593, msdiv25",
  "patthana4.7:69.1": "sc69, ms39P4_1594",
  "patthana4.7:70.1": "sc70, ms39P4_1595, msdiv26",
  "patthana4.7:71.1": "sc71, ms39P4_1596",
  "patthana4.7:72.1": "sc72, ms39P4_1597",
  "patthana4.7:73.1": "sc73, ms39P4_1598, msdiv27",
  "patthana4.7:74.1": "sc74, ms39P4_1599, msdiv28",
  "patthana4.7:75.1": "sc75, ms39P4_1600",
  "patthana4.7:76.1": "sc76, ms39P4_1601",
  "patthana4.7:77.1": "sc77, ms39P4_1602",
  "patthana4.7:78.1": "sc78, ms39P4_1603",
  "patthana4.7:79.1": "sc79, ms39P4_1604, msdiv29",
  "patthana4.7:80.1": "sc80, ms39P4_1605",
  "patthana4.7:81.1": "sc81, ms39P4_1606, msdiv30",
  "patthana4.7:82.1": "sc82, ms39P4_1607",
  "patthana4.7:83.1": "sc83, ms39P4_1608",
  "patthana4.7:84.1": "sc84, ms39P4_1609, msdiv31",
  "patthana4.7:85.1": "sc85, ms39P4_1610",
  "patthana4.7:86.1": "sc86, ms39P4_1611, msdiv32",
  "patthana4.7:87.1": "sc87, ms39P4_1612",
  "patthana4.7:88.1": "sc88, ms39P4_1613",
  "patthana4.7:89.1": "sc89, ms39P4_1614",
  "patthana4.7:90.1": "sc90, ms39P4_1615, msdiv33",
  "patthana4.7:91.1": "sc91, ms39P4_1616",
  "patthana4.7:92.1": "sc92, ms39P4_1617",
  "patthana4.7:93.1": "sc93, ms39P4_1618",
  "patthana4.7:94.1": "sc94, ms39P4_1619, msdiv34",
  "patthana4.7:95.1": "sc95, ms39P4_1620",
  "patthana4.7:96.1": "sc96, ms39P4_1621, msdiv35",
  "patthana4.7:97.1": "sc97, ms39P4_1622",
  "patthana4.7:98.1": "sc98, ms39P4_1623",
  "patthana4.7:99.1": "sc99, ms39P4_1624",
  "patthana4.7:100.1": "sc100, ms39P4_1625, msdiv36",
  "patthana4.7:101.1": "sc101, ms39P4_1626",
  "patthana4.7:102.1": "sc102, ms39P4_1627",
  "patthana4.7:103.1": "sc103, ms39P4_1628",
  "patthana4.7:104.1": "sc104, ms39P4_1629",
  "patthana4.7:105.1": "sc105, ms39P4_1630, msdiv37",
  "patthana4.7:106.1": "sc106, ms39P4_1631, msdiv38",
  "patthana4.7:107.1": "sc107, ms39P4_1632",
  "patthana4.7:108.1": "sc108, ms39P4_1633",
  "patthana4.7:109.1": "sc109, ms39P4_1634, msdiv39",
  "patthana4.7:110.1": "sc110, ms39P4_1635",
  "patthana4.7:111.1": "sc111, ms39P4_1636, msdiv40",
  "patthana4.7:112.1": "sc112, ms39P4_1637",
  "patthana4.7:113.1": "sc113, ms39P4_1638",
  "patthana4.7:114.1": "sc114, ms39P4_1639, msdiv41",
  "patthana4.7:115.1": "sc115, ms39P4_1640",
  "patthana4.7:116.1": "sc116, ms39P4_1641",
  "patthana4.7:117.1": "sc117, ms39P4_1642",
  "patthana4.7:118.1": "sc118, ms39P4_1643",
  "patthana4.7:119.1": "sc119, ms39P4_1644, msdiv42",
  "patthana4.7:120.1": "sc120, ms39P4_1645",
  "patthana4.7:121.1": "sc121, ms39P4_1646, msdiv43",
  "patthana4.7:122.1": "sc122, ms39P4_1647",
  "patthana4.7:123.1": "sc123, ms39P4_1648",
  "patthana4.7:124.1": "sc124, ms39P4_1649, msdiv44",
  "patthana4.7:125.1": "sc125, ms39P4_1650, msdiv45",
  "patthana4.7:126.1": "sc126, ms39P4_1651",
  "patthana4.7:127.1": "sc127, ms39P4_1652",
  "patthana4.7:128.1": "sc128, ms39P4_1653, msdiv46",
  "patthana4.7:129.1": "sc129, ms39P4_1654",
  "patthana4.7:130.1": "sc130, ms39P4_1655",
  "patthana4.7:131.1": "sc131, ms39P4_1656, msdiv47",
  "patthana4.7:132.1": "sc132, ms39P4_1657",
  "patthana4.7:133.1": "sc133, ms39P4_1658, msdiv48",
  "patthana4.7:134.1": "sc134, ms39P4_1659",
  "patthana4.7:135.1": "sc135, ms39P4_1660",
  "patthana4.7:136.1": "sc136, ms39P4_1661, msdiv49",
  "patthana4.7:137.1": "sc137, ms39P4_1662",
  "patthana4.7:138.1": "sc138, ms39P4_1663",
  "patthana4.7:139.1": "sc139, ms39P4_1664",
  "patthana4.7:140.1": "sc140, ms39P4_1665",
  "patthana4.7:141.1": "sc141, ms39P4_1666, msdiv50",
  "patthana4.7:142.1": "sc142, ms39P4_1667",
  "patthana4.7:143.1": "sc143, ms39P4_1668, msdiv51",
  "patthana4.7:144.1": "sc144, ms39P4_1669",
  "patthana4.7:145.1": "sc145, ms39P4_1670",
  "patthana4.7:146.1": "sc146, ms39P4_1671, msdiv52",
  "patthana4.7:147.1": "sc147, ms39P4_1672",
  "patthana4.7:148.1": "sc148, ms39P4_1673, msdiv53",
  "patthana4.7:149.1": "sc149, ms39P4_1674",
  "patthana4.7:150.1": "sc150, ms39P4_1675",
  "patthana4.7:151.1": "sc151, ms39P4_1676",
  "patthana4.7:152.1": "sc152, ms39P4_1677",
  "patthana4.7:153.1": "sc153, ms39P4_1678, msdiv54",
  "patthana4.7:154.1": "sc154, ms39P4_1679, msdiv55",
  "patthana4.7:155.1": "sc155, ms39P4_1680",
  "patthana4.7:156.1": "sc156, ms39P4_1681",
  "patthana4.7:157.1": "sc157, ms39P4_1682, msdiv56",
  "patthana4.7:158.1": "sc158, ms39P4_1683, msdiv57",
  "patthana4.7:159.1": "sc159, ms39P4_1684",
  "patthana4.7:160.1": "sc160, ms39P4_1685",
  "patthana4.7:161.1": "sc161, ms39P4_1686",
  "patthana4.7:162.1": "sc162, ms39P4_1687, msdiv58",
  "patthana4.7:163.1": "sc163, ms39P4_1688",
  "patthana4.7:164.1": "sc164, ms39P4_1689",
  "patthana4.7:165.1": "sc165, ms39P4_1690",
  "patthana4.7:166.1": "sc166, ms39P4_1691, msdiv59",
  "patthana4.7:167.1": "sc167, ms39P4_1692",
  "patthana4.7:168.1": "sc168, ms39P4_1693, msdiv60",
  "patthana4.7:169.1": "sc169, ms39P4_1694",
  "patthana4.7:170.1": "sc170, ms39P4_1695",
  "patthana4.7:171.1": "sc171, ms39P4_1696, msdiv61",
  "patthana4.7:172.1": "sc172, ms39P4_1697",
  "patthana4.7:173.1": "sc173, ms39P4_1698",
  "patthana4.7:174.1": "sc174, ms39P4_1699",
  "patthana4.7:175.1": "sc175, ms39P4_1700",
  "patthana4.7:176.1": "sc176, ms39P4_1701, msdiv62",
  "patthana4.7:177.1": "sc177, ms39P4_1702",
  "patthana4.7:178.1": "sc178, ms39P4_1703, msdiv63",
  "patthana4.7:179.1": "sc179, ms39P4_1704",
  "patthana4.7:180.1": "sc180, ms39P4_1705, msdiv64",
  "patthana4.7:181.1": "sc181, ms39P4_1706",
  "patthana4.7:182.1": "sc182, ms39P4_1707"
}