{
  "patthana2.9:0.1": "<article id='patthana2.9'><header><ul><li class='division'>{}</li>",
  "patthana2.9:0.2": "<li class='subdivision'>{}</li></ul>",
  "patthana2.9:0.3": "<h1>{}</h1></header>",
  "patthana2.9:1.0.1": "<h5>{}</h5>",
  "patthana2.9:1.0.2": "<h6>{}</h6>",
  "patthana2.9:1.1": "<p>{}</p>",
  "patthana2.9:2.1": "<p>{}</p>",
  "patthana2.9:3.1": "<p>{}</p>",
  "patthana2.9:4.1": "<p>{}</p>",
  "patthana2.9:5.1": "<p>{}</p>",
  "patthana2.9:6.0.1": "<h5>{}</h5>",
  "patthana2.9:6.0.2": "<h6>{}</h6>",
  "patthana2.9:6.1": "<p>{}</p>",
  "patthana2.9:7.1": "<p class='endsutta'>{}</p>",
  "patthana2.9:8.0.1": "<h4>{}</h4>",
  "patthana2.9:8.0.2": "<h5>{}</h5>",
  "patthana2.9:8.0.3": "<h6>{}</h6>",
  "patthana2.9:8.1": "<p>{}</p>",
  "patthana2.9:9.0": "<h6>{}</h6>",
  "patthana2.9:9.1": "<p>{}</p>",
  "patthana2.9:10.1": "<p>{}</p>",
  "patthana2.9:11.1": "<p>{}</p>",
  "patthana2.9:12.0.1": "<h5>{}</h5>",
  "patthana2.9:12.0.2": "<h6>{}</h6>",
  "patthana2.9:12.1": "<p>{}</p>",
  "patthana2.9:13.0": "<h6>{}</h6>",
  "patthana2.9:13.1": "<p>{}</p>",
  "patthana2.9:14.0.1": "<h4>{}</h4>",
  "patthana2.9:14.0.2": "<h5>{}</h5>",
  "patthana2.9:14.0.3": "<h6>{}</h6>",
  "patthana2.9:14.1": "<p>{}</p>",
  "patthana2.9:15.0": "<h3>{}</h3>",
  "patthana2.9:15.1": "<p class='pe'>{}</p>",
  "patthana2.9:16.0.1": "<h3>{}</h3>",
  "patthana2.9:16.0.2": "<h4>{}</h4>",
  "patthana2.9:16.0.3": "<h5>{}</h5>",
  "patthana2.9:16.0.4": "<h6>{}</h6>",
  "patthana2.9:16.1": "<p>{}</p>",
  "patthana2.9:17.1": "<p>{}</p>",
  "patthana2.9:18.1": "<p>{}</p>",
  "patthana2.9:19.1": "<p>{}</p>",
  "patthana2.9:20.1": "<p>{}</p>",
  "patthana2.9:21.0.1": "<h5>{}</h5>",
  "patthana2.9:21.0.2": "<h6>{}</h6>",
  "patthana2.9:21.1": "<p>{}</p>",
  "patthana2.9:22.0.1": "<h4>{}</h4>",
  "patthana2.9:22.0.2": "<h5>{}</h5>",
  "patthana2.9:22.0.3": "<h6>{}</h6>",
  "patthana2.9:22.1": "<p>{}</p>",
  "patthana2.9:23.0.1": "<h5>{}</h5>",
  "patthana2.9:23.0.2": "<h6>{}</h6>",
  "patthana2.9:23.1": "<p>{}</p>",
  "patthana2.9:24.0": "<h4>{}</h4>",
  "patthana2.9:24.1": "<p>{}</p>",
  "patthana2.9:25.0": "<h4>{}</h4>",
  "patthana2.9:25.1": "<p>{}</p>",
  "patthana2.9:26.0": "<h3>{}</h3>",
  "patthana2.9:26.1": "<p class='pe'>{}</p>",
  "patthana2.9:27.0": "<h3>{}</h3>",
  "patthana2.9:27.1": "<p>{}</p>",
  "patthana2.9:28.0.1": "<h3>{}</h3>",
  "patthana2.9:28.0.2": "<h4>{}</h4>",
  "patthana2.9:28.0.3": "<h5>{}</h5>",
  "patthana2.9:28.0.4": "<h6>{}</h6>",
  "patthana2.9:28.1": "<p>{}</p>",
  "patthana2.9:29.1": "<p>{}</p>",
  "patthana2.9:30.1": "<p>{}</p>",
  "patthana2.9:31.0": "<h6>{}</h6>",
  "patthana2.9:31.1": "<p>{}</p>",
  "patthana2.9:32.1": "<p>{}</p>",
  "patthana2.9:33.1": "<p>{}</p>",
  "patthana2.9:34.1": "<p>{}</p>",
  "patthana2.9:35.1": "<p>{}</p>",
  "patthana2.9:36.0": "<h6>{}</h6>",
  "patthana2.9:36.1": "<p>{}</p>",
  "patthana2.9:37.1": "<p>{}</p>",
  "patthana2.9:38.1": "<p>{}</p>",
  "patthana2.9:39.1": "<p>{}</p>",
  "patthana2.9:40.1": "<p>{}</p>",
  "patthana2.9:41.0": "<h6>{}</h6>",
  "patthana2.9:41.1": "<p>{}</p>",
  "patthana2.9:42.1": "<p>{}</p>",
  "patthana2.9:43.1": "<p>{}</p>",
  "patthana2.9:44.0": "<h6>{}</h6>",
  "patthana2.9:44.1": "<p>{}</p>",
  "patthana2.9:45.0": "<h6>{}</h6>",
  "patthana2.9:45.1": "<p>{}</p>",
  "patthana2.9:46.1": "<p>{}</p>",
  "patthana2.9:47.1": "<p>{}</p>",
  "patthana2.9:48.1": "<p>{}</p>",
  "patthana2.9:49.1": "<p>{}</p>",
  "patthana2.9:50.0": "<h6>{}</h6>",
  "patthana2.9:50.1": "<p>{}</p>",
  "patthana2.9:51.1": "<p>{}</p>",
  "patthana2.9:52.1": "<p>{}</p>",
  "patthana2.9:53.0": "<h6>{}</h6>",
  "patthana2.9:53.1": "<p>{}</p>",
  "patthana2.9:54.0": "<h6>{}</h6>",
  "patthana2.9:54.1": "<p>{}</p>",
  "patthana2.9:55.0": "<h6>{}</h6>",
  "patthana2.9:55.1": "<p>{}</p>",
  "patthana2.9:56.1": "<p>{}</p>",
  "patthana2.9:57.0": "<h6>{}</h6>",
  "patthana2.9:57.1": "<p>{}</p>",
  "patthana2.9:58.1": "<p>{}</p>",
  "patthana2.9:59.1": "<p>{}</p>",
  "patthana2.9:60.1": "<p>{}</p>",
  "patthana2.9:61.1": "<p>{}</p>",
  "patthana2.9:62.0": "<h6>{}</h6>",
  "patthana2.9:62.1": "<p>{}</p>",
  "patthana2.9:63.1": "<p>{}</p>",
  "patthana2.9:64.1": "<p>{}</p>",
  "patthana2.9:65.1": "<p>{}</p>",
  "patthana2.9:66.1": "<p>{}</p>",
  "patthana2.9:67.0.1": "<h5>{}</h5>",
  "patthana2.9:67.0.2": "<h6>{}</h6>",
  "patthana2.9:67.1": "<p>{}</p>",
  "patthana2.9:68.1": "<p class='endsutta'>{}</p>",
  "patthana2.9:69.0": "<h4>{}</h4>",
  "patthana2.9:69.1": "<p>{}</p>",
  "patthana2.9:70.1": "<p>{}</p>",
  "patthana2.9:71.1": "<p>{}</p>",
  "patthana2.9:72.1": "<p>{}</p>",
  "patthana2.9:73.1": "<p>{}</p>",
  "patthana2.9:74.1": "<p>{}</p>",
  "patthana2.9:75.1": "<p>{}</p>",
  "patthana2.9:76.1": "<p>{}</p>",
  "patthana2.9:77.1": "<p>{}</p>",
  "patthana2.9:78.0.1": "<h4>{}</h4>",
  "patthana2.9:78.0.2": "<h5>{}</h5>",
  "patthana2.9:78.0.3": "<h6>{}</h6>",
  "patthana2.9:78.1": "<p>{}</p>",
  "patthana2.9:79.0": "<h4>{}</h4>",
  "patthana2.9:79.1": "<p>{}</p>",
  "patthana2.9:80.0": "<h4>{}</h4>",
  "patthana2.9:80.1": "<p>{}</p>",
  "patthana2.9:81.1": "<p class='endsutta'>{}</p>",
  "patthana2.9:82.0.1": "<h2>{}</h2>",
  "patthana2.9:82.0.2": "<h3>{}</h3>",
  "patthana2.9:82.0.3": "<h4>{}</h4>",
  "patthana2.9:82.0.4": "<h5>{}</h5>",
  "patthana2.9:82.0.5": "<h6>{}</h6>",
  "patthana2.9:82.1": "<p>{}</p>",
  "patthana2.9:83.1": "<p>{}</p>",
  "patthana2.9:84.1": "<p class='endsutta'>{}</p>",
  "patthana2.9:85.0.1": "<h2>{}</h2>",
  "patthana2.9:85.0.2": "<h3>{}</h3>",
  "patthana2.9:85.0.3": "<h4>{}</h4>",
  "patthana2.9:85.0.4": "<h5>{}</h5>",
  "patthana2.9:85.0.5": "<h6>{}</h6>",
  "patthana2.9:85.1": "<p>{}</p>",
  "patthana2.9:86.1": "<p>{}</p>",
  "patthana2.9:87.1": "<p>{}</p>",
  "patthana2.9:88.1": "<p>{}</p>",
  "patthana2.9:89.1": "<p>{}</p>",
  "patthana2.9:90.0.1": "<h5>{}</h5>",
  "patthana2.9:90.0.2": "<h6>{}</h6>",
  "patthana2.9:90.1": "<p>{}</p>",
  "patthana2.9:91.1": "<p class='endsutta'>{}</p>",
  "patthana2.9:92.0.1": "<h4>{}</h4>",
  "patthana2.9:92.0.2": "<h5>{}</h5>",
  "patthana2.9:92.1": "<p>{}</p>",
  "patthana2.9:93.0": "<h6>{}</h6>",
  "patthana2.9:93.1": "<p>{}</p>",
  "patthana2.9:94.1": "<p>{}</p>",
  "patthana2.9:95.1": "<p>{}</p>",
  "patthana2.9:96.0.1": "<h5>{}</h5>",
  "patthana2.9:96.0.2": "<h6>{}</h6>",
  "patthana2.9:96.1": "<p>{}</p>",
  "patthana2.9:97.0": "<h4>{}</h4>",
  "patthana2.9:97.1": "<p>{}</p>",
  "patthana2.9:98.0": "<h4>{}</h4>",
  "patthana2.9:98.1": "<p>{}</p>",
  "patthana2.9:99.0": "<h3>{}</h3>",
  "patthana2.9:99.1": "<p class='pe'>{}</p>",
  "patthana2.9:100.0.1": "<h3>{}</h3>",
  "patthana2.9:100.0.2": "<h4>{}</h4>",
  "patthana2.9:100.0.3": "<h5>{}</h5>",
  "patthana2.9:100.0.4": "<h6>{}</h6>",
  "patthana2.9:100.1": "<p>{}</p>",
  "patthana2.9:101.1": "<p>{}</p>",
  "patthana2.9:102.1": "<p>{}</p>",
  "patthana2.9:103.1": "<p>{}</p>",
  "patthana2.9:104.1": "<p>{}</p>",
  "patthana2.9:105.1": "<p>{}</p>",
  "patthana2.9:106.1": "<p>{}</p>",
  "patthana2.9:107.0.1": "<h5>{}</h5>",
  "patthana2.9:107.0.2": "<h6>{}</h6>",
  "patthana2.9:107.1": "<p>{}</p>",
  "patthana2.9:108.1": "<p class='endsutta'>{}</p>",
  "patthana2.9:109.0.1": "<h4>{}</h4>",
  "patthana2.9:109.0.2": "<h5>{}</h5>",
  "patthana2.9:109.1": "<p>{}</p>",
  "patthana2.9:110.0.1": "<h5>{}</h5>",
  "patthana2.9:110.0.2": "<h6>{}</h6>",
  "patthana2.9:110.1": "<p>{}</p>",
  "patthana2.9:111.0": "<h4>{}</h4>",
  "patthana2.9:111.1": "<p>{}</p>",
  "patthana2.9:112.0": "<h4>{}</h4>",
  "patthana2.9:112.1": "<p>{}</p>",
  "patthana2.9:113.0": "<h3>{}</h3>",
  "patthana2.9:113.1": "<p class='pe'>{}</p>",
  "patthana2.9:114.0.1": "<h3>{}</h3>",
  "patthana2.9:114.0.2": "<h4>{}</h4>",
  "patthana2.9:114.1": "<p>{}</p>",
  "patthana2.9:115.0.1": "<h5>{}</h5>",
  "patthana2.9:115.0.2": "<h6>{}</h6>",
  "patthana2.9:115.1": "<p>{}</p>",
  "patthana2.9:116.0": "<h3>{}</h3>",
  "patthana2.9:116.1": "<p class='pe'>{}</p>",
  "patthana2.9:117.0.1": "<h3>{}</h3>",
  "patthana2.9:117.0.2": "<h4>{}</h4>",
  "patthana2.9:117.0.3": "<h5>{}</h5>",
  "patthana2.9:117.0.4": "<h6>{}</h6>",
  "patthana2.9:117.1": "<p>{}</p>",
  "patthana2.9:118.1": "<p>{}</p>",
  "patthana2.9:119.0": "<h6>{}</h6>",
  "patthana2.9:119.1": "<p>{}</p>",
  "patthana2.9:120.1": "<p>{}</p>",
  "patthana2.9:121.1": "<p>{}</p>",
  "patthana2.9:122.1": "<p>{}</p>",
  "patthana2.9:123.0": "<h6>{}</h6>",
  "patthana2.9:123.1": "<p>{}</p>",
  "patthana2.9:124.1": "<p>{}</p>",
  "patthana2.9:125.1": "<p>{}</p>",
  "patthana2.9:126.1": "<p>{}</p>",
  "patthana2.9:127.1": "<p>{}</p>",
  "patthana2.9:128.0": "<h6>{}</h6>",
  "patthana2.9:128.1": "<p>{}</p>",
  "patthana2.9:129.1": "<p>{}</p>",
  "patthana2.9:130.1": "<p>{}</p>",
  "patthana2.9:131.1": "<p>{}</p>",
  "patthana2.9:132.0": "<h6>{}</h6>",
  "patthana2.9:132.1": "<p>{}</p>",
  "patthana2.9:133.0": "<h6>{}</h6>",
  "patthana2.9:133.1": "<p>{}</p>",
  "patthana2.9:134.1": "<p>{}</p>",
  "patthana2.9:135.1": "<p>{}</p>",
  "patthana2.9:136.1": "<p>{}</p>",
  "patthana2.9:137.0": "<h6>{}</h6>",
  "patthana2.9:137.1": "<p>{}</p>",
  "patthana2.9:138.1": "<p>{}</p>",
  "patthana2.9:139.0": "<h6>{}</h6>",
  "patthana2.9:139.1": "<p>{}</p>",
  "patthana2.9:140.1": "<p>{}</p>",
  "patthana2.9:141.1": "<p>{}</p>",
  "patthana2.9:142.0": "<h6>{}</h6>",
  "patthana2.9:142.1": "<p>{}</p>",
  "patthana2.9:143.1": "<p>{}</p>",
  "patthana2.9:144.1": "<p>{}</p>",
  "patthana2.9:145.1": "<p>{}</p>",
  "patthana2.9:146.0": "<h6>{}</h6>",
  "patthana2.9:146.1": "<p>{}</p>",
  "patthana2.9:147.1": "<p>{}</p>",
  "patthana2.9:148.1": "<p>{}</p>",
  "patthana2.9:149.0": "<h6>{}</h6>",
  "patthana2.9:149.1": "<p>{}</p>",
  "patthana2.9:150.1": "<p>{}</p>",
  "patthana2.9:151.1": "<p>{}</p>",
  "patthana2.9:152.1": "<p>{}</p>",
  "patthana2.9:153.1": "<p>{}</p>",
  "patthana2.9:154.1": "<p>{}</p>",
  "patthana2.9:155.1": "<p>{}</p>",
  "patthana2.9:156.0.1": "<h5>{}</h5>",
  "patthana2.9:156.0.2": "<h6>{}</h6>",
  "patthana2.9:156.1": "<p>{}</p>",
  "patthana2.9:157.1": "<p class='endsutta'>{}</p>",
  "patthana2.9:158.0": "<h4>{}</h4>",
  "patthana2.9:158.1": "<p>{}</p>",
  "patthana2.9:159.1": "<p>{}</p>",
  "patthana2.9:160.1": "<p>{}</p>",
  "patthana2.9:161.1": "<p>{}</p>",
  "patthana2.9:162.1": "<p>{}</p>",
  "patthana2.9:163.1": "<p>{}</p>",
  "patthana2.9:164.1": "<p>{}</p>",
  "patthana2.9:165.0.1": "<h4>{}</h4>",
  "patthana2.9:165.0.2": "<h5>{}</h5>",
  "patthana2.9:165.0.3": "<h6>{}</h6>",
  "patthana2.9:165.1": "<p>{}</p>",
  "patthana2.9:166.0.1": "<h4>{}</h4>",
  "patthana2.9:166.0.2": "<h6>{}</h6>",
  "patthana2.9:166.1": "<p>{}</p>",
  "patthana2.9:167.0": "<h4>{}</h4>",
  "patthana2.9:167.1": "<p>{}</p>",
  "patthana2.9:168.1": "<p class='endsutta'>{}</p>",
  "patthana2.9:169.0.1": "<h2>{}</h2>",
  "patthana2.9:169.0.2": "<h3>{}</h3>",
  "patthana2.9:169.0.3": "<h4>{}</h4>",
  "patthana2.9:169.0.4": "<h5>{}</h5>",
  "patthana2.9:169.0.5": "<h6>{}</h6>",
  "patthana2.9:169.1": "<p>{}</p>",
  "patthana2.9:170.1": "<p>{}</p>",
  "patthana2.9:171.1": "<p>{}</p>",
  "patthana2.9:172.1": "<p>{}</p>",
  "patthana2.9:173.1": "<p>{}</p>",
  "patthana2.9:174.0": "<h3>{}</h3>",
  "patthana2.9:174.1": "<p class='pe'>{}</p>",
  "patthana2.9:175.0.1": "<h3>{}</h3>",
  "patthana2.9:175.0.2": "<h4>{}</h4>",
  "patthana2.9:175.0.3": "<h5>{}</h5>",
  "patthana2.9:175.0.4": "<h6>{}</h6>",
  "patthana2.9:175.1": "<p>{}</p>",
  "patthana2.9:176.1": "<p>{}</p>",
  "patthana2.9:177.1": "<p>{}</p>",
  "patthana2.9:178.0": "<h6>{}</h6>",
  "patthana2.9:178.1": "<p>{}</p>",
  "patthana2.9:179.1": "<p>{}</p>",
  "patthana2.9:180.1": "<p>{}</p>",
  "patthana2.9:181.1": "<p>{}</p>",
  "patthana2.9:182.1": "<p>{}</p>",
  "patthana2.9:183.1": "<p class='endsutta'>{}</p>",
  "patthana2.9:184.0.1": "<h2>{}</h2>",
  "patthana2.9:184.0.2": "<h3>{}</h3>",
  "patthana2.9:184.0.3": "<h4>{}</h4>",
  "patthana2.9:184.0.4": "<h5>{}</h5>",
  "patthana2.9:184.0.5": "<h6>{}</h6>",
  "patthana2.9:184.1": "<p>{}</p>",
  "patthana2.9:185.1": "<p>{}</p>",
  "patthana2.9:186.1": "<p>{}</p>",
  "patthana2.9:187.1": "<p class='endsutta'>{}</p>",
  "patthana2.9:188.1": "<p class='endsection'>{}</p></article>"
}