{
  "patthana11.15:1.1": "sc1, ms40P11_111, msdiv47",
  "patthana11.15:2.1": "sc2, ms40P11_112",
  "patthana11.15:3.1": "sc3, ms40P11_113, msdiv48",
  "patthana11.15:4.1": "sc4, ms40P11_114",
  "patthana11.15:5.1": "sc5, ms40P11_115, msdiv49",
  "patthana11.15:6.1": "sc6, ms40P11_116",
  "patthana11.15:7.1": "sc7, ms40P11_117, msdiv50",
  "patthana11.15:8.1": "sc8, ms40P11_118",
  "patthana11.15:9.1": "sc9, ms40P11_119, msdiv51",
  "patthana11.15:10.1": "sc10, ms40P11_120",
  "patthana11.15:11.1": "sc11, ms40P11_121, msdiv52",
  "patthana11.15:12.1": "sc12, ms40P11_122",
  "patthana11.15:13.1": "sc13, ms40P11_123, msdiv53",
  "patthana11.15:14.1": "sc14, ms40P11_124",
  "patthana11.15:15.1": "sc15, ms40P11_125, msdiv54",
  "patthana11.15:16.1": "sc16, ms40P11_126, msdiv55",
  "patthana11.15:17.1": "sc17, ms40P11_127",
  "patthana11.15:18.1": "sc18, ms40P11_128, msdiv56",
  "patthana11.15:19.1": "sc19, ms40P11_129",
  "patthana11.15:20.1": "sc20, ms40P11_130, msdiv57",
  "patthana11.15:21.1": "sc21, ms40P11_131, msdiv58",
  "patthana11.15:22.1": "sc22, ms40P11_132, msdiv59",
  "patthana11.15:23.1": "sc23, ms40P11_133, msdiv60",
  "patthana11.15:24.1": "sc24, ms40P11_134, msdiv61",
  "patthana11.15:25.1": "sc25, ms40P11_135, msdiv62"
}