{
  "an5.37:0.1": "Aṅguttara Nikāya 5 ",
  "an5.37:0.2": "4. Sumanavagga ",
  "an5.37:0.3": "37. Bhojanasutta ",
  "an5.37:1.1": "“Bhojanaṁ, bhikkhave, dadamāno dāyako paṭiggāhakānaṁ pañca ṭhānāni deti. ",
  "an5.37:1.2": "Katamāni pañca? ",
  "an5.37:1.3": "Āyuṁ deti, vaṇṇaṁ deti, sukhaṁ deti, balaṁ deti, paṭibhānaṁ deti. ",
  "an5.37:1.4": "Āyuṁ kho pana datvā āyussa bhāgī hoti dibbassa vā mānusassa vā; ",
  "an5.37:1.5": "vaṇṇaṁ datvā vaṇṇassa bhāgī hoti dibbassa vā mānusassa vā; ",
  "an5.37:1.6": "sukhaṁ datvā sukhassa bhāgī hoti dibbassa vā mānusassa vā; ",
  "an5.37:1.7": "balaṁ datvā balassa bhāgī hoti dibbassa vā mānusassa vā; ",
  "an5.37:1.8": "paṭibhānaṁ datvā paṭibhānassa bhāgī hoti dibbassa vā mānusassa vā. ",
  "an5.37:1.9": "Bhojanaṁ, bhikkhave, dadamāno dāyako paṭiggāhakānaṁ imāni pañca ṭhānāni detīti. ",
  "an5.37:2.1": "Āyudo balado dhīro, ",
  "an5.37:2.2": "vaṇṇado paṭibhānado; ",
  "an5.37:2.3": "Sukhassa dātā medhāvī, ",
  "an5.37:2.4": "sukhaṁ so adhigacchati. ",
  "an5.37:3.1": "Āyuṁ datvā balaṁ vaṇṇaṁ, ",
  "an5.37:3.2": "sukhañca paṭibhānakaṁ; ",
  "an5.37:3.3": "Dīghāyu yasavā hoti, ",
  "an5.37:3.4": "yattha yatthūpapajjatī”ti. ",
  "an5.37:3.5": "Sattamaṁ. "
}