{
  "cp11:1.1": "bj38.278, csp1ed21.399, csp2ed21.399, dr33.628, mc2.600, ms21Cp_162, msdiv1, ndp28.400, pts-vp-pli1ed84, pts-vp-pli2ed14, sc1, sya33.568, vri58.385",
  "cp11:2.1": "ms21Cp_163, msdiv2, sc2",
  "cp11:3.1": "ms21Cp_164, msdiv3, sc3",
  "cp11:4.1": "ms21Cp_165, msdiv4, sc4",
  "cp11:5.1": "ms21Cp_166, msdiv5, sc5",
  "cp11:6.1": "ms21Cp_167, msdiv6, sc6",
  "cp11:7.1": "ms21Cp_168, msdiv7, sc7",
  "cp11:8.1": "ms21Cp_169, msdiv8, sc8",
  "cp11:9.1": "dr33.629, mc2.601, ms21Cp_170, msdiv9, sc9, sya33.569",
  "cp11:10.1": "ms21Cp_171, msdiv10, sc10",
  "cp11:11.1": "ms21Cp_172, sc11"
}