{
  "an7.62:0.1": "Aṅguttara Nikāya 7 ",
  "an7.62:0.2": "6. Abyākatavagga ",
  "an7.62:0.3": "62. Mettasutta ",
  "an7.62:1.1": "“Mā, bhikkhave, puññānaṁ bhāyittha. ",
  "an7.62:1.2": "Sukhassetaṁ, bhikkhave, adhivacanaṁ yadidaṁ puññāni. ",
  "an7.62:1.3": "Abhijānāmi kho panāhaṁ, bhikkhave, dīgharattaṁ katānaṁ puññānaṁ dīgharattaṁ iṭṭhaṁ kantaṁ manāpaṁ vipākaṁ paccanubhūtaṁ. ",
  "an7.62:1.4": "Satta vassāni mettacittaṁ bhāvesiṁ. ",
  "an7.62:1.5": "Satta vassāni mettacittaṁ bhāvetvā satta saṁvaṭṭavivaṭṭakappe nayimaṁ lokaṁ punāgamāsiṁ. ",
  "an7.62:1.6": "Saṁvaṭṭamāne sudāhaṁ, bhikkhave, loke ābhassarūpago homi, ",
  "an7.62:1.7": "vivaṭṭamāne loke suññaṁ brahmavimānaṁ upapajjāmi. ",
  "an7.62:2.1": "Tatra sudaṁ, bhikkhave, brahmā homi mahābrahmā abhibhū anabhibhūto aññadatthudaso vasavattī. ",
  "an7.62:2.2": "Chattiṁsakkhattuṁ kho panāhaṁ, bhikkhave, sakko ahosiṁ devānamindo; ",
  "an7.62:2.3": "anekasatakkhattuṁ rājā ahosiṁ cakkavattī dhammiko dhammarājā cāturanto vijitāvī janapadatthāvariyappatto sattaratanasamannāgato. ",
  "an7.62:2.4": "Tassa mayhaṁ, bhikkhave, imāni satta ratanāni ahesuṁ, seyyathidaṁ—",
  "an7.62:2.5": "cakkaratanaṁ, hatthiratanaṁ, assaratanaṁ, maṇiratanaṁ, itthiratanaṁ, gahapatiratanaṁ, pariṇāyakaratanameva sattamaṁ. ",
  "an7.62:2.6": "Parosahassaṁ kho pana me, bhikkhave, puttā ahesuṁ sūrā vīraṅgarūpā parasenappamaddanā. ",
  "an7.62:2.7": "So imaṁ pathaviṁ sāgarapariyantaṁ adaṇḍena asatthena dhammena abhivijiya ajjhāvasinti. ",
  "an7.62:3.1": "Passa puññānaṁ vipākaṁ, ",
  "an7.62:3.2": "Kusalānaṁ sukhesino; ",
  "an7.62:3.3": "Mettaṁ cittaṁ vibhāvetvā, ",
  "an7.62:3.4": "Satta vassāni bhikkhavo; ",
  "an7.62:3.5": "Sattasaṁvaṭṭavivaṭṭakappe, ",
  "an7.62:3.6": "Nayimaṁ lokaṁ punāgamiṁ. ",
  "an7.62:4.1": "Saṁvaṭṭamāne lokamhi, ",
  "an7.62:4.2": "homi ābhassarūpago; ",
  "an7.62:4.3": "Vivaṭṭamāne lokasmiṁ, ",
  "an7.62:4.4": "suññabrahmūpago ahuṁ. ",
  "an7.62:5.1": "Sattakkhattuṁ mahābrahmā, ",
  "an7.62:5.2": "vasavattī tadā ahuṁ; ",
  "an7.62:5.3": "Chattiṁsakkhattuṁ devindo, ",
  "an7.62:5.4": "devarajjamakārayiṁ. ",
  "an7.62:6.1": "Cakkavattī ahuṁ rājā, ",
  "an7.62:6.2": "jambumaṇḍassa issaro; ",
  "an7.62:6.3": "Muddhāvasitto khattiyo, ",
  "an7.62:6.4": "manussādhipatī ahuṁ. ",
  "an7.62:7.1": "Adaṇḍena asatthena, ",
  "an7.62:7.2": "vijeyya pathaviṁ imaṁ; ",
  "an7.62:7.3": "Asāhasena kammena, ",
  "an7.62:7.4": "samena manusāsi taṁ. ",
  "an7.62:8.1": "Dhammena rajjaṁ kāretvā, ",
  "an7.62:8.2": "asmiṁ pathavimaṇḍale; ",
  "an7.62:8.3": "Mahaddhane mahābhoge, ",
  "an7.62:8.4": "aḍḍhe ajāyihaṁ kule. ",
  "an7.62:9.1": "Sabbakāmehi sampanne, ",
  "an7.62:9.2": "ratanehi ca sattahi; ",
  "an7.62:9.3": "Buddhā saṅgāhakā loke, ",
  "an7.62:9.4": "tehi etaṁ sudesitaṁ. ",
  "an7.62:10.1": "Eso hetu mahantassa, ",
  "an7.62:10.2": "pathabyo me na vipajjati; ",
  "an7.62:10.3": "Pahūtavittūpakaraṇo, ",
  "an7.62:10.4": "rājā hoti patāpavā. ",
  "an7.62:11.1": "Iddhimā yasavā hoti, ",
  "an7.62:11.2": "jambumaṇḍassa issaro; ",
  "an7.62:11.3": "Ko sutvā nappasīdeyya, ",
  "an7.62:11.4": "api kaṇhābhijātiyo. ",
  "an7.62:12.1": "Tasmā hi attakāmena, ",
  "an7.62:12.2": "mahattamabhikaṅkhatā; ",
  "an7.62:12.3": "Saddhammo garukātabbo, ",
  "an7.62:12.4": "saraṁ buddhānasāsanan”ti. ",
  "an7.62:12.5": "Navamaṁ. "
}