{
  "ds2.1.1:1.1": "bj41.26, csp1ed29.17, csp2ed29.17, dr34.21, lv1.18, ms29Dhs_368, msdiv1, ndp29.18, pts-vp-pli9, sc1, sya34.9, vri113.21",
  "ds2.1.1:2.1": "ms29Dhs_369, sc2",
  "ds2.1.1:3.1": "cck29.10, ms29Dhs_370, sc3",
  "ds2.1.1:4.1": "ms29Dhs_371, sc4",
  "ds2.1.1:5.1": "ms29Dhs_372, sc5",
  "ds2.1.1:6.1": "lv1.19, ms29Dhs_373, sc6",
  "ds2.1.1:7.1": "ms29Dhs_374, sc7",
  "ds2.1.1:8.1": "ms29Dhs_375, sc8",
  "ds2.1.1:9.1": "ms29Dhs_376, sc9, sya34.10",
  "ds2.1.1:10.1": "ms29Dhs_377, ndp29.19, sc10",
  "ds2.1.1:11.1": "ms29Dhs_378, sc11",
  "ds2.1.1:12.1": "ms29Dhs_379, sc12",
  "ds2.1.1:13.1": "dr34.22, lv1.20, ms29Dhs_380, sc13",
  "ds2.1.1:14.1": "csp1ed29.18, csp2ed29.18, ms29Dhs_381, msdiv2, sc14, vri113.22",
  "ds2.1.1:15.1": "cck29.11, ms29Dhs_382, msdiv3, pts-vp-pli10, sc15",
  "ds2.1.1:16.1": "lv1.21, ms29Dhs_383, msdiv4, sc16",
  "ds2.1.1:17.1": "ms29Dhs_384, msdiv5, sc17",
  "ds2.1.1:18.1": "bj41.28, ms29Dhs_385, msdiv6, sc18",
  "ds2.1.1:19.1": "lv1.22, ms29Dhs_386, msdiv7, sc19, sya34.11",
  "ds2.1.1:20.1": "dr34.23, ms29Dhs_387, msdiv8, sc20",
  "ds2.1.1:21.1": "cck29.12, ms29Dhs_388, msdiv9, sc21",
  "ds2.1.1:22.1": "csp1ed29.19, csp2ed29.19, lv1.23, ms29Dhs_389, msdiv10, ndp29.20, sc22, vri113.23",
  "ds2.1.1:23.1": "ms29Dhs_390, msdiv11, sc23",
  "ds2.1.1:24.1": "lv1.24, ms29Dhs_391, msdiv12, pts-vp-pli11, sc24",
  "ds2.1.1:25.1": "bj41.30, ms29Dhs_392, msdiv13, sc25, sya34.12",
  "ds2.1.1:26.1": "cck29.13, lv1.25, ms29Dhs_393, msdiv14, sc26",
  "ds2.1.1:27.1": "dr34.24, ms29Dhs_394, msdiv15, sc27",
  "ds2.1.1:28.1": "csp1ed29.20, csp2ed29.20, lv1.26, ms29Dhs_395, msdiv16, ndp29.21, sc28, vri113.24",
  "ds2.1.1:29.1": "ms29Dhs_396, msdiv17, sc29, sya34.13",
  "ds2.1.1:30.1": "bj41.32, cck29.14, lv1.27, ms29Dhs_397, msdiv18, sc30",
  "ds2.1.1:31.1": "ms29Dhs_398, msdiv19, pts-vp-pli12, sc31",
  "ds2.1.1:32.1": "dr34.25, lv1.28, ms29Dhs_399, msdiv20, sc32",
  "ds2.1.1:33.1": "ms29Dhs_400, msdiv21, sc33",
  "ds2.1.1:34.1": "csp1ed29.21, csp2ed29.21, lv1.29, ms29Dhs_401, msdiv22, ndp29.22, sc34, sya34.14, vri113.25",
  "ds2.1.1:35.1": "cck29.15, ms29Dhs_402, msdiv23, sc35",
  "ds2.1.1:36.1": "bj41.34, lv1.30, ms29Dhs_403, msdiv24, sc36",
  "ds2.1.1:37.1": "ms29Dhs_404, msdiv25, sc37",
  "ds2.1.1:38.1": "dr34.26, ms29Dhs_405, msdiv26, pts-vp-pli13, sc38, sya34.15",
  "ds2.1.1:39.1": "lv1.31, ms29Dhs_406, msdiv27, sc39",
  "ds2.1.1:40.1": "cck29.16, ms29Dhs_407, msdiv28, ndp29.23, sc40",
  "ds2.1.1:41.1": "csp1ed29.22, csp2ed29.22, lv1.32, ms29Dhs_408, msdiv29, sc41, vri113.26",
  "ds2.1.1:42.1": "ms29Dhs_409, msdiv30, sc42",
  "ds2.1.1:43.1": "bj41.36, lv1.33, ms29Dhs_410, msdiv31, sc43, sya34.16",
  "ds2.1.1:44.1": "dr34.27, ms29Dhs_411, msdiv32, sc44",
  "ds2.1.1:45.1": "cck29.17, ms29Dhs_412, msdiv33, sc45",
  "ds2.1.1:46.1": "lv1.34, ms29Dhs_413, msdiv34, ndp29.24, pts-vp-pli14, sc46",
  "ds2.1.1:47.1": "csp1ed29.23, csp2ed29.23, ms29Dhs_414, msdiv35, sc47, vri113.27",
  "ds2.1.1:48.1": "lv1.35, ms29Dhs_415, msdiv36, sc48, sya34.17",
  "ds2.1.1:49.1": "bj41.38, cck29.18, dr34.28, lv1.36, ms29Dhs_416, msdiv37, sc49",
  "ds2.1.1:50.1": "ms29Dhs_417, msdiv38, sc50",
  "ds2.1.1:51.1": "ms29Dhs_418, msdiv39, sc51",
  "ds2.1.1:52.1": "lv1.37, ms29Dhs_419, msdiv40, sc52",
  "ds2.1.1:53.1": "ms29Dhs_420, msdiv41, ndp29.25, pts-vp-pli15, sc53, sya34.18",
  "ds2.1.1:54.1": "cck29.19, csp1ed29.24, csp2ed29.24, ms29Dhs_421, msdiv42, sc54, vri113.28",
  "ds2.1.1:55.1": "dr34.29, lv1.38, ms29Dhs_422, msdiv43, sc55",
  "ds2.1.1:56.1": "ms29Dhs_423, msdiv44, sc56",
  "ds2.1.1:57.1": "bj41.40, ms29Dhs_424, msdiv45, sc57",
  "ds2.1.1:58.1": "lv1.39, ms29Dhs_425, msdiv46, sc58",
  "ds2.1.1:59.1": "ms29Dhs_426, msdiv47, sc59, sya34.19",
  "ds2.1.1:60.1": "cck29.20, ms29Dhs_427, msdiv48, sc60",
  "ds2.1.1:61.1": "lv1.40, ms29Dhs_428, msdiv49, ndp29.26, sc61",
  "ds2.1.1:62.1": "dr34.30, ms29Dhs_429, msdiv50, pts-vp-pli16, sc62, vri113.29",
  "ds2.1.1:63.1": "csp1ed29.25, csp2ed29.25, ms29Dhs_430, msdiv51, sc63",
  "ds2.1.1:64.1": "lv1.41, ms29Dhs_431, msdiv52, sc64",
  "ds2.1.1:65.1": "bj41.42, cck29.21, ms29Dhs_432, msdiv53, sc65, sya34.20",
  "ds2.1.1:66.1": "lv1.42, ms29Dhs_433, msdiv54, sc66",
  "ds2.1.1:67.1": "dr34.31, lv1.43, ms29Dhs_434, msdiv55, ndp29.27, sc67",
  "ds2.1.1:68.1": "csp1ed29.26, csp2ed29.26, ms29Dhs_435, msdiv56, sc68, sya34.21, vri113.30",
  "ds2.1.1:69.1": "cck29.22, lv1.44, ms29Dhs_436, msdiv57, pts-vp-pli17, sc69",
  "ds2.1.1:70.1": "ms29Dhs_437, sc70",
  "ds2.1.1:70.3": "ms29Dhs_438",
  "ds2.1.1:71.1": "bj41.44, lv1.45, ms29Dhs_439, msdiv58, sc71",
  "ds2.1.1:72.1": "dr34.32, ms29Dhs_440, msdiv59, ndp29.28, sc72, sya34.22, vri113.31",
  "ds2.1.1:73.1": "cck29.23, csp1ed29.27, csp2ed29.27, lv1.46, ms29Dhs_441, msdiv60, sc73",
  "ds2.1.1:74.1": "ms29Dhs_442, msdiv61, sc74",
  "ds2.1.1:75.1": "lv1.47, ms29Dhs_443, msdiv62, pts-vp-pli18, sc75",
  "ds2.1.1:76.1": "bj41.46, cck29.24, dr34.33, lv1.48, ms29Dhs_444, msdiv63, sc76, sya34.23",
  "ds2.1.1:76.4": "ms29Dhs_445",
  "ds2.1.1:77.1": "ms29Dhs_446, msdiv64, ndp29.29, sc77",
  "ds2.1.1:78.1": "ms29Dhs_447, msdiv65, sc78, vri113.32",
  "ds2.1.1:79.1": "csp1ed29.28, csp2ed29.28, ms29Dhs_448, msdiv66, sc79",
  "ds2.1.1:79.4": "ms29Dhs_449",
  "ds2.1.1:80.1": "lv1.49, ms29Dhs_450, msdiv67, sc80",
  "ds2.1.1:81.1": "ms29Dhs_451, msdiv68, sc81",
  "ds2.1.1:82.1": "ms29Dhs_452, msdiv69, pts-vp-pli19, sc82",
  "ds2.1.1:82.4": "ms29Dhs_453",
  "ds2.1.1:83.1": "ms29Dhs_454, msdiv70, sc83, sya34.24",
  "ds2.1.1:84.1": "cck29.25, dr34.34, lv1.50, ms29Dhs_455, msdiv71, sc84",
  "ds2.1.1:85.1": "ms29Dhs_456, msdiv72, ndp29.30, sc85",
  "ds2.1.1:86.1": "bj41.48, ms29Dhs_457, msdiv73, sc86, vri113.33",
  "ds2.1.1:86.4": "ms29Dhs_458",
  "ds2.1.1:87.1": "csp1ed29.29, csp2ed29.29, lv1.51, ms29Dhs_459, msdiv74, sc87",
  "ds2.1.1:88.1": "ms29Dhs_460, msdiv75, sc88",
  "ds2.1.1:89.1": "lv1.52, ms29Dhs_461, msdiv76, sc89",
  "ds2.1.1:90.1": "cck29.26, dr34.35, ms29Dhs_462, msdiv77, sc90, sya34.25",
  "ds2.1.1:91.1": "ms29Dhs_463, msdiv78, pts-vp-pli20, sc91",
  "ds2.1.1:92.1": "lv1.53, ms29Dhs_464, msdiv79, ndp29.31, sc92, vri113.34",
  "ds2.1.1:93.1": "bj41.50, ms29Dhs_465, msdiv80, sc93",
  "ds2.1.1:94.1": "csp1ed29.30, csp2ed29.30, lv1.54, ms29Dhs_466, msdiv81, sc94",
  "ds2.1.1:95.1": "cck29.27, dr34.36, ms29Dhs_467, msdiv82, sc95, sya34.26",
  "ds2.1.1:95.4": "ms29Dhs_468",
  "ds2.1.1:96.1": "ms29Dhs_469, msdiv83, sc96",
  "ds2.1.1:97.1": "lv1.55, ms29Dhs_470, msdiv84, sc97",
  "ds2.1.1:98.1": "ms29Dhs_471, msdiv85, sc98",
  "ds2.1.1:99.1": "ms29Dhs_472, msdiv86, ndp29.32, pts-vp-pli21, sc99, vri113.35",
  "ds2.1.1:100.1": "lv1.56, ms29Dhs_473, msdiv87, sc100",
  "ds2.1.1:101.1": "bj41.52, ms29Dhs_474, msdiv88, sc101",
  "ds2.1.1:101.4": "ms29Dhs_475",
  "ds2.1.1:102.1": "cck29.28, csp1ed29.31, csp2ed29.31, dr34.37, ms29Dhs_476, msdiv89, sc102",
  "ds2.1.1:103.1": "lv1.57, ms29Dhs_477, msdiv90, sc103, sya34.27",
  "ds2.1.1:104.1": "ms29Dhs_478, msdiv91, sc104",
  "ds2.1.1:105.1": "lv1.58, ms29Dhs_479, msdiv92, ndp29.33, sc105, vri113.36",
  "ds2.1.1:106.1": "ms29Dhs_480, msdiv93, pts-vp-pli22, sc106",
  "ds2.1.1:107.1": "cck29.29, dr34.38, lv1.59, ms29Dhs_481, msdiv94, sc107, sya34.28",
  "ds2.1.1:107.4": "ms29Dhs_482",
  "ds2.1.1:108.1": "bj41.54, csp1ed29.32, csp2ed29.32, ms29Dhs_483, msdiv95, sc108",
  "ds2.1.1:109.1": "ms29Dhs_484, msdiv96, sc109",
  "ds2.1.1:110.1": "lv1.60, ms29Dhs_485, msdiv97, sc110",
  "ds2.1.1:111.1": "ms29Dhs_486, msdiv98, sc111",
  "ds2.1.1:112.1": "lv1.61, ms29Dhs_487, msdiv99, ndp29.34, sc112, vri113.37",
  "ds2.1.1:113.1": "cck29.30, dr34.39, ms29Dhs_488, msdiv100, pts-vp-pli23, sc113, sya34.29",
  "ds2.1.1:114.1": "lv1.62, ms29Dhs_489, msdiv101, sc114",
  "ds2.1.1:115.1": "csp1ed29.33, csp2ed29.33, ms29Dhs_490, msdiv102, sc115",
  "ds2.1.1:115.4": "ms29Dhs_491",
  "ds2.1.1:116.1": "ms29Dhs_492, msdiv103, sc116",
  "ds2.1.1:117.1": "bj41.56, lv1.63, ms29Dhs_493, msdiv104, sc117",
  "ds2.1.1:118.1": "ms29Dhs_494, msdiv105, sc118, vri113.38",
  "ds2.1.1:119.1": "cck29.31, dr34.40, lv1.64, ms29Dhs_495, msdiv106, ndp29.35, sc119, sya34.30",
  "ds2.1.1:119.4": "ms29Dhs_496",
  "ds2.1.1:120.1": "ms29Dhs_497, msdiv107, sc120",
  "ds2.1.1:121.1": "ms29Dhs_498, msdiv108, sc121",
  "ds2.1.1:122.1": "lv1.65, ms29Dhs_499, msdiv109, pts-vp-pli24, sc122",
  "ds2.1.1:123.1": "csp1ed29.34, csp2ed29.34, ms29Dhs_500, msdiv110, sc123",
  "ds2.1.1:124.1": "cck29.32, dr34.41, ms29Dhs_501, msdiv111, sc124, sya34.31",
  "ds2.1.1:125.1": "lv1.66, ms29Dhs_502, msdiv112, sc125",
  "ds2.1.1:126.1": "bj41.58, ms29Dhs_503, msdiv113, sc126, vri113.39",
  "ds2.1.1:127.1": "cck29.33, lv1.67, ms29Dhs_504, msdiv114, ndp29.36, sc127, sya34.32",
  "ds2.1.1:128.1": "csp1ed29.35, csp2ed29.35, dr34.42, lv1.68, ms29Dhs_505, msdiv115, sc128",
  "ds2.1.1:129.1": "ms29Dhs_506, msdiv116, pts-vp-pli25, sc129",
  "ds2.1.1:130.1": "ms29Dhs_507, msdiv117, sc130",
  "ds2.1.1:131.1": "lv1.69, ms29Dhs_508, msdiv118, sc131, vri113.40",
  "ds2.1.1:132.1": "cck29.34, ms29Dhs_509, msdiv119, ndp29.37, sc132, sya34.33",
  "ds2.1.1:133.1": "bj41.60, ms29Dhs_510, msdiv120, sc133",
  "ds2.1.1:134.1": "dr34.43, ms29Dhs_511, sc134",
  "ds2.1.1:134.3": "ms29Dhs_512",
  "ds2.1.1:135.1": "csp1ed29.36, csp2ed29.36, lv1.70, ms29Dhs_513, msdiv121, sc135",
  "ds2.1.1:136.1": "lv1.71, ms29Dhs_514, msdiv122, sc136",
  "ds2.1.1:137.1": "cck29.35, ms29Dhs_515, msdiv123, pts-vp-pli26, sc137, sya34.34, vri113.41",
  "ds2.1.1:138.1": "ms29Dhs_516, msdiv124, sc138",
  "ds2.1.1:139.1": "dr34.44, ms29Dhs_517, msdiv125, sc139",
  "ds2.1.1:140.1": "lv1.72, ms29Dhs_518, msdiv126, ndp29.38, sc140",
  "ds2.1.1:141.1": "ms29Dhs_519, msdiv127, sc141",
  "ds2.1.1:142.1": "bj41.62, ms29Dhs_520, msdiv128, sc142",
  "ds2.1.1:143.1": "ms29Dhs_521, msdiv129, sc143",
  "ds2.1.1:144.1": "csp1ed29.37, csp2ed29.37, lv1.73, ms29Dhs_522, msdiv130, sc144",
  "ds2.1.1:145.1": "ms29Dhs_523, msdiv131, sc145, sya34.35",
  "ds2.1.1:146.1": "cck29.36, ms29Dhs_524, msdiv132, sc146, vri113.42",
  "ds2.1.1:147.1": "ms29Dhs_525, msdiv133, sc147",
  "ds2.1.1:148.1": "dr34.45, lv1.74, ms29Dhs_526, msdiv134, sc148",
  "ds2.1.1:149.1": "ms29Dhs_527, msdiv135, sc149",
  "ds2.1.1:150.1": "ms29Dhs_528, msdiv136, sc150",
  "ds2.1.1:151.1": "ms29Dhs_529, msdiv137, sc151",
  "ds2.1.1:152.1": "ms29Dhs_530, msdiv138, ndp29.39, sc152",
  "ds2.1.1:153.1": "lv1.75, ms29Dhs_531, msdiv139, sc153",
  "ds2.1.1:154.1": "ms29Dhs_532, msdiv140, sc154",
  "ds2.1.1:155.1": "bj41.64, ms29Dhs_533, msdiv141, sc155, sya34.36",
  "ds2.1.1:156.1": "cck29.37, csp1ed29.38, csp2ed29.38, ms29Dhs_534, msdiv142, sc156",
  "ds2.1.1:157.1": "ms29Dhs_535, msdiv143, sc157, vri113.43",
  "ds2.1.1:158.1": "dr34.46, ms29Dhs_536, msdiv144, sc158",
  "ds2.1.1:159.1": "lv1.76, ms29Dhs_537, msdiv145, sc159",
  "ds2.1.1:160.1": "ms29Dhs_538, sc160",
  "ds2.1.1:160.3": "ms29Dhs_539",
  "ds2.1.1:161.1": "lv1.77, ms29Dhs_540, msdiv146, pts-vp-pli27, sc161",
  "ds2.1.1:161.5": "ms29Dhs_541",
  "ds2.1.1:162.1": "cck29.38, csp1ed29.39, csp2ed29.39, dr34.47, lv1.78, ms29Dhs_542, msdiv147, ndp29.40, sc162, sya34.37, vri113.44",
  "ds2.1.1:163.1": "bj41.66, cck29.39, lv1.79, ms29Dhs_543, sc163, sya34.38",
  "ds2.1.1:164.1": "dr34.48, lv1.80, ms29Dhs_544, msdiv148, ndp29.41, pts-vp-pli28, sc164",
  "ds2.1.1:164.6": "ms29Dhs_545",
  "ds2.1.1:165.1": "cck29.40, csp1ed29.40, csp2ed29.40, lv1.81, ms29Dhs_546, msdiv149, sc165, sya34.39, vri113.45",
  "ds2.1.1:165.5": "ms29Dhs_547",
  "ds2.1.1:166.1": "bj41.68, cck29.41, dr34.49, lv1.82, lv1.83, ms29Dhs_548, msdiv150, ndp29.42, sc166, sya34.40",
  "ds2.1.1:167.1": "ms29Dhs_549, msdiv151, sc167",
  "ds2.1.1:168.1": "csp1ed29.41, csp2ed29.41, lv1.84, ms29Dhs_550, msdiv152, sc168, vri113.46",
  "ds2.1.1:169.1": "ms29Dhs_551, msdiv153, sc169",
  "ds2.1.1:170.1": "cck29.42, dr34.50, lv1.85, ms29Dhs_552, msdiv154, sc170",
  "ds2.1.1:171.1": "ms29Dhs_553, sc171, sya34.41",
  "ds2.1.1:172.1": "bj41.70, lv1.86, ms29Dhs_554, msdiv155, ndp29.43, pts-vp-pli29, sc172",
  "ds2.1.1:173.1": "cck29.43, csp1ed29.42, csp2ed29.42, dr34.51, lv1.87, ms29Dhs_555, sc173, vri113.47",
  "ds2.1.1:173.4": "ms29Dhs_556",
  "ds2.1.1:174.1": "ms29Dhs_557, msdiv156, sc174, sya34.42",
  "ds2.1.1:174.5": "ms29Dhs_558",
  "ds2.1.1:175.1": "cck29.44, csp1ed29.43, csp2ed29.43, dr34.52, lv1.88, lv1.89, ms29Dhs_559, msdiv157, ndp29.44, sc175, sya34.43",
  "ds2.1.1:176.1": "bj41.72, lv1.90, ms29Dhs_560, pts-vp-pli30, sc176, vri113.48",
  "ds2.1.1:177.1": "cck29.45, lv1.91, ms29Dhs_561, msdiv158, sc177",
  "ds2.1.1:178.1": "ms29Dhs_562, sc178, sya34.44",
  "ds2.1.1:178.4": "ms29Dhs_563",
  "ds2.1.1:179.1": "dr34.53, lv1.92, ms29Dhs_564, msdiv159, ndp29.45, sc179",
  "ds2.1.1:179.5": "ms29Dhs_565"
}