{
  "ja438:1.1": "sc1, ms22J_1896, msdiv105",
  "ja438:2.1": "sc2, ms22J_1897, msdiv106",
  "ja438:3.1": "sc3, ms22J_1898, msdiv107",
  "ja438:4.1": "sc4, pts-vp-pli3.540, ms22J_1899, msdiv108",
  "ja438:5.1": "sc5, pts-vp-pli3.541, ms22J_1900, msdiv109",
  "ja438:6.1": "sc6, ms22J_1901, msdiv110",
  "ja438:7.1": "sc7, ms22J_1902, msdiv111",
  "ja438:8.1": "sc8, ms22J_1903, msdiv112",
  "ja438:9.1": "sc9, pts-vp-pli3.542, ms22J_1904, msdiv113",
  "ja438:10.1": "sc10, ms22J_1905",
  "ja438:11.1": "sc11, ms22J_1906",
  "ja438:12.1": "sc12, ms22J_1907",
  "ja438:13.1": "sc13, ms22J_1908"
}