{
  "ja360:0.2": "ca → va (sya1ed, sya2ed, pts-vp-pli1) ",
  "ja360:1.3": "suyonandī → ito hi susandhī (bj, sya1ed, sya2ed); itopi sussondī (pts-vp-pli1) ",
  "ja360:2.2": "sedumaṁ → serumaṁ (bj, sya1ed, sya2ed, pts-vp-pli1) ",
  "ja360:2.4": "saggasamāgamo → aggasamāgamo (sya1ed, sya2ed) ",
  "ja360:3.1": "Kurukacchā → bharukacchā (bj, sya1ed, sya2ed); bharukaccha (pts-vp-pli1) ",
  "ja360:3.3": "Makarehi abhidā → makarehambhidā (bj); maṅkarehi bhidā (sya1ed, sya2ed); makarehi bhinnā (pts-vp-pli1) ",
  "ja360:4.3": "Aṅgena → aṅkena (bj, pts-vp-pli1, mr) ",
  "ja360:6.1": "Suyonandījātakaṁ → susandhijātakaṁ (bj); susandhījātakaṁ (sya1ed, sya2ed); sussondijātakaṁ (pts-vp-pli1) "
}