{
  "ja487:1.2": "Dummakkharūpā → dummudharūpā (bj, mr); dummukharūpā (pts-vp-pli1) | mantaṁ jappanti → yeme japanti (bj, pts-vp-pli1); ye mantaṁ japanti (sya1ed, sya2ed); ye'me jappanti mante (ja377:3 [Setaketujātaka])",
  "ja487:2.1": "karetha → karotha (bj, pts-vp-pli1); kareyya (sya1ed, sya2ed); katvāna (ja377:4 [Setaketujātaka])",
  "ja487:2.4": "pamucce → pamuñce (sya1ed, sya2ed, pts-vp-pli1)",
  "ja487:4.3": "Kittiñhi → kittiñca (sya1ed, sya2ed)",
  "ja487:4.4": "puṇāti → puṇoti (bj); puṇeti (sya1ed, sya2ed ja377:6 [Setaketujātaka]); puneti (pts-vp-pli1)",
  "ja487:5.2": "so → bho (sya1ed, sya2ed, mr)",
  "ja487:5.3": "bhoto → bhoti (mr)",
  "ja487:5.4": "sottiyākulavaṁsako → sotthiyākulavaṁsako (bj, pts-vp-pli1); sotthiyakulavaṁsato (sya1ed, sya2ed)",
  "ja487:11.6": "seyyotha → seyyova (bj, pts-vp-pli1)",
  "ja487:14.3": "Panatthaṁ → pasatthaṁ (sya1ed, sya2ed); panaṭṭhaṁ (pts-vp-pli1); pasaṭṭhaṁ (mr)",
  "ja487:16.1": "Evameva → evamevaṁ (pts-vp-pli1)",
  "ja487:16.3": "sajātiṁ pamuñcanti → na tesaṁ jātiṁ pucchanti (bj, sya1ed, sya2ed, pts-vp-pli1); na tesaṁ jāti sujjhati (mr)"
}