{
  "thag16.1:1.1": "<section class='sutta' id='thag16.1'><article><div class='hgroup'><p class='division'>",
  "thag16.1:2.1": "</p><p>",
  "thag16.1:3.1": "</p><p>",
  "thag16.1:4.1": "</p><h1>",
  "thag16.1:5.1": "</h1></div><blockquote class='gatha'><p><a class='sc' id='1'></a><a class='vns' id='vns705'></a><a class='vnp' id='vnp705'></a><a class='pts' id='pts71'></a>",
  "thag16.1:5.2": "<br>",
  "thag16.1:5.3": "<br>",
  "thag16.1:5.4": "<br>",
  "thag16.1:6.1": "</p><p><a class='sc' id='2'></a><a class='vns' id='vns706'></a><a class='vnp' id='vnp706'></a>",
  "thag16.1:6.2": "<br>",
  "thag16.1:6.3": "<br>",
  "thag16.1:6.4": "<br>",
  "thag16.1:7.1": "</p><p><a class='sc' id='3'></a><a class='vns' id='vns707'></a><a class='vnp' id='vnp707'></a>",
  "thag16.1:7.2": "<br>",
  "thag16.1:7.3": "<br>",
  "thag16.1:7.4": "<br>",
  "thag16.1:8.1": "</p><p><a class='sc' id='4'></a><a class='vns' id='vns708'></a><a class='vnp' id='vnp708'></a>",
  "thag16.1:8.2": "<br>",
  "thag16.1:8.3": "<br>",
  "thag16.1:8.4": "<br>",
  "thag16.1:9.1": "</p><p><a class='sc' id='5'></a><a class='vns' id='vns709'></a><a class='vnp' id='vnp709'></a>",
  "thag16.1:9.2": "<br>",
  "thag16.1:9.3": "<br>",
  "thag16.1:9.4": "<br>",
  "thag16.1:10.1": "</p><p><a class='sc' id='6'></a><a class='vns' id='vns710'></a><a class='vnp' id='vnp710'></a>",
  "thag16.1:10.2": "<br>",
  "thag16.1:10.3": "<br>",
  "thag16.1:10.4": "<br>",
  "thag16.1:11.1": "</p><p><a class='sc' id='7'></a><a class='vns' id='vns711'></a><a class='vnp' id='vnp711'></a>",
  "thag16.1:11.2": "<br>",
  "thag16.1:11.3": "<br>",
  "thag16.1:11.4": "<br>",
  "thag16.1:12.1": "</p><p><a class='sc' id='8'></a><a class='vns' id='vns712'></a><a class='vnp' id='vnp712'></a>",
  "thag16.1:12.2": "<br>",
  "thag16.1:12.3": "<br>",
  "thag16.1:12.4": "<br>",
  "thag16.1:13.1": "</p><p><a class='sc' id='9'></a><a class='vns' id='vns713'></a><a class='vnp' id='vnp713'></a>",
  "thag16.1:13.2": "<br>",
  "thag16.1:13.3": "<br>",
  "thag16.1:13.4": "<br>",
  "thag16.1:14.1": "</p><p><a class='sc' id='10'></a><a class='vns' id='vns714'></a><a class='vnp' id='vnp714'></a>",
  "thag16.1:14.2": "<br>",
  "thag16.1:14.3": "<br>",
  "thag16.1:14.4": "<br>",
  "thag16.1:15.1": "</p><p><a class='sc' id='11'></a><a class='vns' id='vns715'></a><a class='vnp' id='vnp715'></a>",
  "thag16.1:15.2": "<br>",
  "thag16.1:15.3": "<br>",
  "thag16.1:15.4": "<br>",
  "thag16.1:16.1": "</p><p><a class='sc' id='12'></a><a class='vns' id='vns716'></a><a class='vnp' id='vnp716'></a>",
  "thag16.1:16.2": "<br>",
  "thag16.1:16.3": "<br>",
  "thag16.1:16.4": "<br>",
  "thag16.1:17.1": "</p><p><a class='sc' id='13'></a><a class='vns' id='vns717'></a><a class='vnp' id='vnp717'></a>",
  "thag16.1:17.2": "<br>",
  "thag16.1:17.3": "<br>",
  "thag16.1:17.4": "<br>",
  "thag16.1:18.1": "</p><p><a class='sc' id='14'></a><a class='vns' id='vns718'></a><a class='vnp' id='vnp718'></a><a class='pts' id='pts72'></a>",
  "thag16.1:18.2": "<br>",
  "thag16.1:18.3": "<br>",
  "thag16.1:18.4": "<br>",
  "thag16.1:19.1": "</p><p><a class='sc' id='15'></a><a class='vns' id='vns719'></a><a class='vnp' id='vnp719'></a>",
  "thag16.1:19.2": "<br>",
  "thag16.1:19.3": "<br>",
  "thag16.1:19.4": "<br>",
  "thag16.1:20.1": "</p><p><a class='sc' id='16'></a><a class='vns' id='vns720'></a><a class='vnp' id='vnp720'></a>",
  "thag16.1:20.2": "<br>",
  "thag16.1:20.3": "<br>",
  "thag16.1:20.4": "<br>",
  "thag16.1:21.1": "</p><p><a class='sc' id='17'></a><a class='vns' id='vns721'></a><a class='vnp' id='vnp721'></a>",
  "thag16.1:21.2": "<br>",
  "thag16.1:21.3": "<br>",
  "thag16.1:21.4": "<br>",
  "thag16.1:22.1": "</p><p><a class='sc' id='18'></a><a class='vns' id='vns722'></a><a class='vnp' id='vnp722'></a>",
  "thag16.1:22.2": "<br>",
  "thag16.1:22.3": "<br>",
  "thag16.1:22.4": "<br>",
  "thag16.1:23.1": "</p><p><a class='sc' id='19'></a><a class='vns' id='vns723'></a><a class='vnp' id='vnp723'></a>",
  "thag16.1:23.2": "<br>",
  "thag16.1:23.3": "<br>",
  "thag16.1:23.4": "<br>",
  "thag16.1:24.1": "</p><p><a class='sc' id='20'></a><a class='vns' id='vns724'></a><a class='vnp' id='vnp724'></a>",
  "thag16.1:24.2": "<br>",
  "thag16.1:24.3": "<br>",
  "thag16.1:24.4": "<br>",
  "thag16.1:25.1": "</p><p><a class='sc' id='21'></a><a class='vns' id='vns725'></a><a class='vnp' id='vnp725'></a>",
  "thag16.1:25.2": "<br>",
  "thag16.1:25.3": "<br>",
  "thag16.1:25.4": "<br>",
  "thag16.1:26.1": "</p></blockquote><p class='endsutta'>",
  "thag16.1:26.2": "",
  "~": "</p></article></section></section></body></html>"
}