{
  "an4.183:0.1": "<article id='an4.183'><header><ul><li class='division'>{}</li>",
  "an4.183:0.2": "<li>{}</li></ul>",
  "an4.183:0.3": "<h1 class='sutta-title'>{}</h1></header>",
  "an4.183:1.1": "<p>{}",
  "an4.183:1.2": "{}",
  "an4.183:1.3": "{}</p>",
  "an4.183:2.1": "<p>{}",
  "an4.183:2.2": "{}",
  "an4.183:2.3": "{}",
  "an4.183:2.4": "{}",
  "an4.183:2.5": "{}",
  "an4.183:2.6": "{}",
  "an4.183:2.7": "{}",
  "an4.183:2.8": "{}",
  "an4.183:2.9": "{}</p>",
  "an4.183:3.1": "<p>{}",
  "an4.183:3.2": "{}",
  "an4.183:3.3": "{}",
  "an4.183:3.4": "{}",
  "an4.183:3.5": "{}",
  "an4.183:3.6": "{}",
  "an4.183:3.7": "{}",
  "an4.183:3.8": "{}</p>",
  "an4.183:4.1": "<p>{}",
  "an4.183:4.2": "{}</p>",
  "an4.183:5.1": "<p>{}",
  "an4.183:5.2": "{}</p>",
  "an4.183:6.1": "<p>{}",
  "an4.183:6.2": "{}</p>",
  "an4.183:7.1": "<p>{}",
  "an4.183:7.2": "{}</p>",
  "an4.183:8.1": "<p>{}</p>",
  "an4.183:8.2": "<p class='endsutta'>{}</p></article>"
}