{
    "pdhp195:0.0": "<section class='range' id='pdhp195-215'><header><ul><li class='division'>{}</li></ul>",
    "pdhp195:0.1": "<h1>{}</h1></header>",
    "pdhp195:1": "<article id='pdhp195'><blockquote class='gatha'><p><span class='verse-line'>{}</span>",
    "pdhp195:2": "<span class='verse-line'>{}</span></p></blockquote></article>",
    "pdhp196:1": "<article id='pdhp196'><blockquote class='gatha'><p><span class='verse-line'>{}</span>",
    "pdhp196:2": "<span class='verse-line'>{}</span></p></blockquote></article>",
    "pdhp197:1": "<article id='pdhp197'><blockquote class='gatha'><p><span class='verse-line'>{}</span>",
    "pdhp197:2": "<span class='verse-line'>{}</span></p></blockquote></article>",
    "pdhp198:1": "<article id='pdhp198'><blockquote class='gatha'><p><span class='verse-line'>{}</span>",
    "pdhp198:2": "<span class='verse-line'>{}</span></p></blockquote></article>",
    "pdhp199:1": "<article id='pdhp199'><blockquote class='gatha'><p><span class='verse-line'>{}</span>",
    "pdhp199:2": "<span class='verse-line'>{}</span></p></blockquote></article>",
    "pdhp200:1": "<article id='pdhp200'><blockquote class='gatha'><p><span class='verse-line'>{}</span>",
    "pdhp200:2": "<span class='verse-line'>{}</span></p></blockquote></article>",
    "pdhp201:1": "<article id='pdhp201'><blockquote class='gatha'><p><span class='verse-line'>{}</span>",
    "pdhp201:2": "<span class='verse-line'>{}</span>",
    "pdhp201:3": "<span class='verse-line'>{}</span></p></blockquote></article>",
    "pdhp202:1": "<article id='pdhp202'><blockquote class='gatha'><p><span class='verse-line'>{}</span>",
    "pdhp202:2": "<span class='verse-line'>{}</span></p></blockquote></article>",
    "pdhp203:1": "<article id='pdhp203'><blockquote class='gatha'><p><span class='verse-line'>{}</span>",
    "pdhp203:2": "<span class='verse-line'>{}</span></p></blockquote></article>",
    "pdhp204:1": "<article id='pdhp204'><blockquote class='gatha'><p><span class='verse-line'>{}</span>",
    "pdhp204:2": "<span class='verse-line'>{}</span></p></blockquote></article>",
    "pdhp205:1": "<article id='pdhp205'><blockquote class='gatha'><p><span class='verse-line'>{}</span>",
    "pdhp205:2": "<span class='verse-line'>{}</span>",
    "pdhp205:3": "<span class='verse-line'>{}</span></p></blockquote></article>",
    "pdhp206:1": "<article id='pdhp206'><blockquote class='gatha'><p><span class='verse-line'>{}</span>",
    "pdhp206:2": "<span class='verse-line'>{}</span>",
    "pdhp206:3": "<span class='verse-line'>{}</span></p></blockquote></article>",
    "pdhp207:1": "<article id='pdhp207'><blockquote class='gatha'><p><span class='verse-line'>{}</span>",
    "pdhp207:2": "<span class='verse-line'>{}</span></p></blockquote></article>",
    "pdhp208:1": "<article id='pdhp208'><blockquote class='gatha'><p><span class='verse-line'>{}</span>",
    "pdhp208:2": "<span class='verse-line'>{}</span></p></blockquote></article>",
    "pdhp209:1": "<article id='pdhp209'><blockquote class='gatha'><p><span class='verse-line'>{}</span>",
    "pdhp209:2": "<span class='verse-line'>{}</span></p></blockquote></article>",
    "pdhp210:1": "<article id='pdhp210'><blockquote class='gatha'><p><span class='verse-line'>{}</span>",
    "pdhp210:2": "<span class='verse-line'>{}</span></p></blockquote></article>",
    "pdhp211:1": "<article id='pdhp211'><blockquote class='gatha'><p><span class='verse-line'>{}</span>",
    "pdhp211:2": "<span class='verse-line'>{}</span></p></blockquote></article>",
    "pdhp212:1": "<article id='pdhp212'><blockquote class='gatha'><p><span class='verse-line'>{}</span>",
    "pdhp212:2": "<span class='verse-line'>{}</span></p></blockquote></article>",
    "pdhp213:1": "<article id='pdhp213'><blockquote class='gatha'><p><span class='verse-line'>{}</span>",
    "pdhp213:2": "<span class='verse-line'>{}</span></p></blockquote></article>",
    "pdhp214:1": "<article id='pdhp214'><blockquote class='gatha'><p><span class='verse-line'>{}</span>",
    "pdhp214:2": "<span class='verse-line'>{}</span></p></blockquote></article>",
    "pdhp215:1": "<article id='pdhp215'><blockquote class='gatha'><p><span class='verse-line'>{}</span>",
    "pdhp215:2": "<span class='verse-line'>{}</span></p></blockquote>",
    "pdhp215:3": "<p class='endsection'><span class='verse-line'>{}</span></p></article></section>"
}