{
  "sn46.20:0.1": "Saṁyutta Nikāya 46.20 ",
  "sn46.20:0.2": "2. Gilānavagga ",
  "sn46.20:0.3": "Nibbidāsutta ",
  "sn46.20:1.1": "“Sattime, bhikkhave, bojjhaṅgā bhāvitā bahulīkatā ekantanibbidāya virāgāya nirodhāya upasamāya abhiññāya sambodhāya nibbānāya saṁvattanti. ",
  "sn46.20:1.2": "Katame satta? ",
  "sn46.20:1.3": "Satisambojjhaṅgo …pe… upekkhāsambojjhaṅgo—",
  "sn46.20:1.4": "ime kho, bhikkhave, satta bojjhaṅgā bhāvitā bahulīkatā ekantanibbidāya virāgāya nirodhāya upasamāya abhiññāya sambodhāya nibbānāya saṁvattantī”ti. ",
  "sn46.20:1.5": "Dasamaṁ. ",
  "sn46.20:1.6": "Gilānavaggo dutiyo. ",
  "sn46.20:2.0": "Tassuddānaṁ ",
  "sn46.20:2.1": "Pāṇā sūriyūpamā dve, ",
  "sn46.20:2.2": "gilānā apare tayo; ",
  "sn46.20:2.3": "Pāraṅgāmī viraddho ca, ",
  "sn46.20:2.4": "ariyo nibbidāya cāti. "
}