{
  "dn12:1.1": "pts-cs1, pts-vp-pli1.224, sc1",
  "dn12:2.1": "pts-cs2, sc2",
  "dn12:3.1": "pts-cs3, pts-vp-pli1.225, sc3",
  "dn12:4.1": "pts-cs4, sc4",
  "dn12:5.1": "pts-cs5, sc5",
  "dn12:6.1": "pts-cs6, pts-vp-pli1.226, sc6",
  "dn12:7.1": "pts-cs7, sc7",
  "dn12:7.7": "sc8",
  "dn12:8.1": "pts-cs8",
  "dn12:9.1": "pts-cs9, pts-vp-pli1.227, sc9",
  "dn12:9.4": "sc10",
  "dn12:10.1": "pts-cs10",
  "dn12:10.8": "sc11",
  "dn12:11.1": "pts-cs11, sc12",
  "dn12:11.8": "pts-vp-pli1.228, sc13",
  "dn12:12.1": "pts-cs12, sc14",
  "dn12:13.1": "pts-cs13",
  "dn12:14.1": "pts-cs14, pts-vp-pli1.229, sc15",
  "dn12:15.1": "pts-cs15",
  "dn12:16.1": "pts-cs16, sc16",
  "dn12:17.1": "pts-cs17, pts-vp-pli1.231, sc17",
  "dn12:18.1": "pts-cs18, pts-vp-pli1.232, sc18",
  "dn12:19.1": "pts-cs19, sc19",
  "dn12:20-55.1": "pts-cs20-55, pts-vp-pli1.233, sc20",
  "dn12:56-62.1": "pts-cs56-62, sc21",
  "dn12:63-77.1": "pts-cs63-77, sc22",
  "dn12:63-77.4": "pts-vp-pli1.234, sc23",
  "dn12:78.1": "pts-cs78, sc24"
}